{
  "adjacency_nodes": 5,
  "confusion": {
    "0->0": 33,
    "0->1": 12,
    "1->0": 2,
    "1->1": 53
  },
  "coop_confusion": {
    "0->0": 33,
    "0->1": 12,
    "1->0": 2,
    "1->1": 53
  },
  "coop_heuristic_confusion": {
    "0->0": 29,
    "0->1": 16,
    "1->0": 3,
    "1->1": 52
  },
  "coop_heuristic_val_accuracy": 0.81,
  "coop_no_direction_confusion": {
    "0->0": 32,
    "0->1": 13,
    "1->0": 1,
    "1->1": 54
  },
  "coop_no_direction_pred_distribution": {
    "0": 33,
    "1": 67
  },
  "coop_no_direction_val_accuracy": 0.86,
  "coop_no_interaction_confusion": {
    "0->0": 34,
    "0->1": 11,
    "1->0": 1,
    "1->1": 54
  },
  "coop_no_interaction_pred_distribution": {
    "0": 35,
    "1": 65
  },
  "coop_no_interaction_val_accuracy": 0.88,
  "coop_no_neighbor_confusion": {
    "0->0": 39,
    "0->1": 6,
    "1->0": 9,
    "1->1": 46
  },
  "coop_no_neighbor_pred_distribution": {
    "0": 48,
    "1": 52
  },
  "coop_no_neighbor_val_accuracy": 0.85,
  "coop_pred_distribution": {
    "0": 35,
    "1": 65
  },
  "coop_temporal_confusion": {
    "0->0": 33,
    "0->1": 12,
    "1->0": 2,
    "1->1": 53
  },
  "coop_temporal_pred_distribution": {
    "0": 35,
    "1": 65
  },
  "coop_temporal_val_accuracy": 0.86,
  "coop_val_accuracy": 0.86,
  "eval_story": {
    "cooperative_gain_over_local": 0.01,
    "directional_gain_within_coop": 0.0,
    "full_coop_gain_over_graph_lite": -0.02,
    "graph_lite_gain_over_local": 0.03,
    "graph_lite_gain_over_simple_fusion": -0.01,
    "interaction_gain_within_coop": -0.02,
    "label_balance_gap_train_val": 0.6,
    "ml_coop_gain_over_heuristic_coop": 0.05,
    "sample_per_timestep": 5.0,
    "simple_fusion_gain_over_local": 0.04,
    "temporal_coop_gain_over_coop": 0.0,
    "temporal_coop_gain_over_local": 0.01
  },
  "graph_lite_confusion": {
    "0->0": 34,
    "0->1": 11,
    "1->0": 1,
    "1->1": 54
  },
  "graph_lite_pred_distribution": {
    "0": 35,
    "1": 65
  },
  "graph_lite_val_accuracy": 0.88,
  "label_distribution": {
    "0": 255,
    "1": 245
  },
  "local_confusion": {
    "0->0": 37,
    "0->1": 8,
    "1->0": 7,
    "1->1": 48
  },
  "local_pred_distribution": {
    "0": 44,
    "1": 56
  },
  "local_val_accuracy": 0.85,
  "pred_distribution": {
    "0": 35,
    "1": 65
  },
  "rows": 500,
  "samples": 500,
  "simple_fusion_confusion": {
    "0->0": 35,
    "0->1": 10,
    "1->0": 1,
    "1->1": 54
  },
  "simple_fusion_pred_distribution": {
    "0": 36,
    "1": 64
  },
  "simple_fusion_val_accuracy": 0.89,
  "source_csv": "/Users/v120674/Documents/RMIt/SonHa/traffic-heir-prototype/data/sumo/raw/large_states.csv",
  "split_mode": "temporal",
  "timesteps": 100,
  "train": 400,
  "train_distribution": {
    "0": 210,
    "1": 190
  },
  "uses_adjacency": true,
  "val": 100,
  "val_accuracy": 0.86,
  "val_distribution": {
    "0": 45,
    "1": 55
  }
}